trogon/__init__.py
trogon/constants.py
trogon/detect_run_string.py
trogon/introspect.py
trogon/run_command.py
trogon/trogon.py
trogon/trogon.scss
trogon/widgets/__init__.py
trogon/widgets/about.py
trogon/widgets/command_info.py
trogon/widgets/command_tree.py
trogon/widgets/form.py
trogon/widgets/multiple_choice.py
trogon/widgets/parameter_controls.py
trogon-0.5.0.dist-info/METADATA
trogon-0.5.0.dist-info/WHEEL
trogon-0.5.0.dist-info/RECORD
